opensesame_plugins/evt_plugins/__init__.py
opensesame_plugins/evt_plugins/evt_trigger/__init__.py
opensesame_plugins/evt_plugins/evt_trigger/evt_trigger.md
opensesame_plugins/evt_plugins/evt_trigger/evt_trigger.png
opensesame_plugins/evt_plugins/evt_trigger/evt_trigger.py
opensesame_plugins/evt_plugins/evt_trigger/evt_trigger_large.png
opensesame_plugins/evt_plugins/response_box/__init__.py
opensesame_plugins/evt_plugins/response_box/response_box.md
opensesame_plugins/evt_plugins/response_box/response_box.png
opensesame_plugins/evt_plugins/response_box/response_box.py
opensesame_plugins/evt_plugins/response_box/response_box_large.png
opensesame_plugins/evt_plugins/rgb_led_control/__init__.py
opensesame_plugins/evt_plugins/rgb_led_control/rgb_led_control.md
opensesame_plugins/evt_plugins/rgb_led_control/rgb_led_control.png
opensesame_plugins/evt_plugins/rgb_led_control/rgb_led_control.py
opensesame_plugins/evt_plugins/rgb_led_control/rgb_led_control_large.png
opensesame_plugins/evt_plugins/rsp_pygame/__init__.py
opensesame_plugins/evt_plugins/rsp_pygame/_libjoystick/__init__.py
opensesame_plugins/evt_plugins/rsp_pygame/_libjoystick/basejoystick.py
opensesame_plugins/evt_plugins/rsp_pygame/_libjoystick/legacy.py
opensesame_plugins/evt_plugins/rsp_pygame/libjoystick.py
opensesame_plugins/evt_plugins/rsp_pygame/rsp_pygame.md
opensesame_plugins/evt_plugins/rsp_pygame/rsp_pygame.png
opensesame_plugins/evt_plugins/rsp_pygame/rsp_pygame.py
opensesame_plugins/evt_plugins/rsp_pygame/rsp_pygame_large.png
opensesame_plugins/evt_plugins/tactile_stimulator/__init__.py
opensesame_plugins/evt_plugins/tactile_stimulator/tactile_stimulator.md
opensesame_plugins/evt_plugins/tactile_stimulator/tactile_stimulator.png
opensesame_plugins/evt_plugins/tactile_stimulator/tactile_stimulator.py
opensesame_plugins/evt_plugins/tactile_stimulator/tactile_stimulator_large.png
opensesame_plugins/evt_plugins/vas_gui/__init__.py
opensesame_plugins/evt_plugins/vas_gui/vas_gui.md
evt_plugins-0.2.1.dist-info/LICENSE
evt_plugins-0.2.1.dist-info/METADATA
evt_plugins-0.2.1.dist-info/WHEEL
evt_plugins-0.2.1.dist-info/RECORD
