Metadata-Version: 2.3
Name: evt-plugins
Version: 0.2.1
Summary: RUG/BSS EVT-plugins for OpenSesame 4
License: GPL-3.0-or-later
Keywords: evt,api,usb,hid,psychology,response-box
Author: Mark M. Span
Author-email: m.m.span@rug.nl
Maintainer: Martin Stokroos
Maintainer-email: m.stokroos@rug.nl
Requires-Python: >=3.8,<4.0
Classifier: License :: OSI Approved :: GNU General Public License v3 or later (GPLv3+)
Classifier: Programming Language :: Python :: 3
Classifier: Programming Language :: Python :: 3.8
Classifier: Programming Language :: Python :: 3.9
Classifier: Programming Language :: Python :: 3.10
Classifier: Programming Language :: Python :: 3.11
Classifier: Programming Language :: Python :: 3.12
Classifier: Programming Language :: Python :: 3.13
Requires-Dist: pyevt (>=0.2.0,<0.3.0)
Project-URL: Documentation, https://github.com/MartinStokroos/pyevt/wiki
Project-URL: Homepage, https://github.com/MartinStokroos/pyevt
Project-URL: Repository, https://github.com/MartinStokroos/pyevt
